latqcdtools/__init__.py
latqcdtools/legacy.py
latqcdtools/testing.py
latqcdtools/base/__init__.py
latqcdtools/base/check.py
latqcdtools/base/cleanData.py
latqcdtools/base/initialize.py
latqcdtools/base/logger.py
latqcdtools/base/plotting.py
latqcdtools/base/printErrorBars.py
latqcdtools/base/readWrite.py
latqcdtools/base/speedify.py
latqcdtools/base/utilities.py
latqcdtools/interfaces/HotQCD.py
latqcdtools/interfaces/MILC.py
latqcdtools/interfaces/__init__.py
latqcdtools/interfaces/confReader.py
latqcdtools/interfaces/interfaces.py
latqcdtools/interfaces/lime.py
latqcdtools/interfaces/simulationManagement.py
latqcdtools/math/SU2.py
latqcdtools/math/SU3.py
latqcdtools/math/__init__.py
latqcdtools/math/math.py
latqcdtools/math/num_deriv.py
latqcdtools/math/num_int.py
latqcdtools/math/optimize.py
latqcdtools/math/polynomials.py
latqcdtools/math/spline.py
latqcdtools/physics/HRG.py
latqcdtools/physics/HotQCDEOS.py
latqcdtools/physics/__init__.py
latqcdtools/physics/constants.py
latqcdtools/physics/continuumExtrap.py
latqcdtools/physics/denseObs.py
latqcdtools/physics/diracFreespectra.py
latqcdtools/physics/gauge.py
latqcdtools/physics/ideal.py
latqcdtools/physics/lattice.py
latqcdtools/physics/lattice_params.py
latqcdtools/physics/polyakovTools.py
latqcdtools/physics/referenceScales.py
latqcdtools/physics/runningCoupling.py
latqcdtools/physics/staticPotential.py
latqcdtools/physics/statisticalPhysics.py
latqcdtools/statistics/__init__.py
latqcdtools/statistics/autocorrelation.py
latqcdtools/statistics/bootstr.py
latqcdtools/statistics/fitting.py
latqcdtools/statistics/jackknife.py
latqcdtools/statistics/statistics.py
latqcdtools-1.3.1.dist-info/licenses/LICENSE
latqcdtools-1.3.1.dist-info/METADATA
latqcdtools-1.3.1.dist-info/WHEEL
latqcdtools-1.3.1.dist-info/top_level.txt
latqcdtools-1.3.1.dist-info/RECORD
