Metadata-Version: 2.4
Name: latqcdtools
Version: 1.3.1
Summary: A set of Python tools for statistically analyzing correlated data. This includes aspects of lattice QCD applications related to QCD phenomenology.
Home-page: https://github.com/LatticeQCD/AnalysisToolbox
Author: D. A. Clarke
Author-email: clarke.davida@gmail.com
Classifier: Programming Language :: Python :: 3
Classifier: License :: OSI Approved :: MIT License
Classifier: Operating System :: OS Independent
Requires-Python: >=3.9
License-File: LICENSE
Requires-Dist: colorama
Requires-Dist: matplotlib
Requires-Dist: numba
Requires-Dist: numpy
Requires-Dist: pathos
Requires-Dist: PyQt5
Requires-Dist: pytest
Requires-Dist: pyyaml
Requires-Dist: scipy
Requires-Dist: sympy
Dynamic: author
Dynamic: author-email
Dynamic: classifier
Dynamic: description
Dynamic: description-content-type
Dynamic: home-page
Dynamic: license-file
Dynamic: requires-dist
Dynamic: requires-python
Dynamic: summary
